pyvpc/__init__.py
pyvpc/pyvpc.py
pyvpc/pyvpc_cidr_block.py
test/__init__.py
test/test_pyvpc.py
pyvpc-0.1.8.dist-info/LICENSE
pyvpc-0.1.8.dist-info/METADATA
pyvpc-0.1.8.dist-info/WHEEL
pyvpc-0.1.8.dist-info/entry_points.txt
pyvpc-0.1.8.dist-info/top_level.txt
pyvpc-0.1.8.dist-info/RECORD
