Metadata-Version: 2.1
Name: pyvpc
Version: 0.1.8
Summary: Python AWS VPC CIDR available range finder with sub networks
Home-page: https://github.com/ArieLevs/PyVPC
Author: Arie Lev
Author-email: levinsonarie@gmail.com
License: Apache License 2.0
Keywords: Networking,IPv4,IP,CIDR,VPC,AWS,Subnet,Range,Network Suggestion
Platform: UNKNOWN
Classifier: Programming Language :: Python :: 3
Classifier: Programming Language :: Python :: 3.7
Classifier: License :: OSI Approved :: Apache Software License
Classifier: Operating System :: OS Independent
Requires-Dist: boto3 (==1.17.13)
Requires-Dist: tabulate (==0.8.9)
